[{"system":"SchoolBright-Library","environment":"development","branch":"release/development","version":"v1.0.6","build":"f2fab3d","updated_at":"2025-06-26T03:41:40+00:00","description":"Add auto-assign configuration for PRs","deployed_by":"thanatschoolbright","repo":"sb-web-library"},{"system":"AlphaTutor-System","environment":"development","branch":"release/development","version":"","build":"81e8d35","updated_at":"2025-06-26T04:04:17+00:00","description":"Update version display colors for better visibility and add auto-assign configuration for PRs","deployed_by":"thanatschoolbright","repo":"apt-web-system"},{"system":"SchoolBright-Academic","environment":"production","branch":"release/production","version":"","build":"08dadf66b","updated_at":"2025-06-27T23:40:27+00:00","description":"Merge pull request #44 from Jabjai-Corporation/release/beta","deployed_by":"netkrishnan","repo":"sb-web-academic"},{"system":"SchoolBright-Mark-Activity","environment":"development","branch":"release/development","version":"1.0.0","build":"a990a1f","updated_at":"2025-06-30T02:26:49+00:00","description":"Merge pull request #11 from Jabjai-Corporation/dev/kang","deployed_by":"Tech Lead - Light","repo":"sb-web-mark_activity"},{"system":"SchoolBright-Mark-Activity","environment":"production","branch":"release/production","version":"1.0.0","build":"a3da338","updated_at":"2025-06-30T03:22:25+00:00","description":"Merge pull request #12 from Jabjai-Corporation/release/development","deployed_by":"Tech Lead - Light","repo":"sb-web-mark_activity"},{"system":"SchoolBright-System","environment":"beta","branch":"release/beta","version":"v.2.0.0","build":"4875590","updated_at":"2025-06-30T08:23:39+00:00","description":"Merge pull request #160 from Jabjai-Corporation/release/development","deployed_by":"tanakongsengwan","repo":"sb-web-system"},{"system":"SchoolBright-System","environment":"production","branch":"release/production","version":"v.2.0.0","build":"488efef","updated_at":"2025-06-30T08:32:38+00:00","description":"Merge pull request #161 from Jabjai-Corporation/release/beta","deployed_by":"tanakongsengwan","repo":"sb-web-system"},{"system":"SchoolBright-Accounting","environment":"production","branch":"release/production","version":"1.0.0","build":"253b98eb","updated_at":"2025-06-30T14:58:12+00:00","description":"Merge pull request #245 from Jabjai-Corporation/release/development","deployed_by":"Apisit Promjanya","repo":"sb-web-accounting-system"},{"system":"SchoolBright-Academic","environment":"beta","branch":"release/beta","version":"","build":"19e46d54e","updated_at":"2025-07-01T01:10:03+00:00","description":"Merge pull request #46 from Jabjai-Corporation/release/development","deployed_by":"netkrishnan","repo":"sb-web-academic"},{"system":"SchoolBright-System","environment":"development","branch":"release/development","version":"v.2.0.0","build":"e4fe830","updated_at":"2025-07-01T03:42:35+00:00","description":"Merge branch 'release/development' of https://github.com/Jabjai-Corporation/sb-web-system into release/development","deployed_by":"thanatschoolbright","repo":"sb-web-system"},{"system":"SchoolBright-Canteen-Web","environment":"development","branch":"release/development","version":"","build":"e2628fc","updated_at":"2025-07-01T03:44:18+00:00","description":"Update version.json to build 39","deployed_by":"thanatschoolbright","repo":"sb-web-shop"},{"system":"SchoolBright-Accounting","environment":"development","branch":"release/development","version":"1.0.0","build":"d5859c4a","updated_at":"2025-07-01T06:02:57+00:00","description":"Merge pull request #247 from Jabjai-Corporation/dev-apisit","deployed_by":"Apisit Promjanya","repo":"sb-web-accounting-system"},{"system":"SchoolBright-Academic","environment":"development","branch":"release/development","version":"","build":"d67196698","updated_at":"2025-07-01T06:22:45+00:00","description":"Merge pull request #48 from Jabjai-Corporation/dev/krishnan/AcademicSetting","deployed_by":"netkrishnan","repo":"sb-web-academic"}]
